pyQuranDownloader/__init__.py
pyQuranDownloader/__qurandownloader.py
pyQuranDownloader/__reciter.py
pyQuranDownloader-1.0.1.dist-info/METADATA
pyQuranDownloader-1.0.1.dist-info/WHEEL
pyQuranDownloader-1.0.1.dist-info/top_level.txt
pyQuranDownloader-1.0.1.dist-info/RECORD
